pywisc/command_line.py
pywisc/escalares.py
pywisc/evaluacion.py
pywisc/prueba.py
pywisc/wisc.py
pywisc/data/data_4_es.json
pywisc/data/wisc_4_es_ar.json
pywisc/tools/__init__.py
pywisc/tools/csv_drive.py
pywisc/tools/tmpdata/.keep
pywisc/tools/tmpdata/wisc-4-es-ar-10_0-10_3.csv
pywisc/tools/tmpdata/wisc-4-es-ar-10_4-10_7.csv
pywisc/tools/tmpdata/wisc-4-es-ar-10_8-10_11.csv
pywisc/tools/tmpdata/wisc-4-es-ar-11_0-11_3.csv
pywisc/tools/tmpdata/wisc-4-es-ar-11_4-11_7.csv
pywisc/tools/tmpdata/wisc-4-es-ar-11_8-11_11.csv
pywisc/tools/tmpdata/wisc-4-es-ar-12_0-12_3.csv
pywisc/tools/tmpdata/wisc-4-es-ar-12_4-12_7.csv
pywisc/tools/tmpdata/wisc-4-es-ar-12_8-12_11.csv
pywisc/tools/tmpdata/wisc-4-es-ar-13_0-13_3.csv
pywisc/tools/tmpdata/wisc-4-es-ar-13_4-13_7.csv
pywisc/tools/tmpdata/wisc-4-es-ar-13_8-13_11.csv
pywisc/tools/tmpdata/wisc-4-es-ar-14_0-14_3.csv
pywisc/tools/tmpdata/wisc-4-es-ar-14_4-14_7.csv
pywisc/tools/tmpdata/wisc-4-es-ar-14_8-14_11.csv
pywisc/tools/tmpdata/wisc-4-es-ar-15-0-15-3.csv
pywisc/tools/tmpdata/wisc-4-es-ar-15_0-15_3.csv
pywisc/tools/tmpdata/wisc-4-es-ar-15_4-15_7.csv
pywisc/tools/tmpdata/wisc-4-es-ar-15_8-15_11.csv
pywisc/tools/tmpdata/wisc-4-es-ar-6-0-6-3.csv
pywisc/tools/tmpdata/wisc-4-es-ar-6_0-6_3.csv
pywisc/tools/tmpdata/wisc-4-es-ar-6_4-6_7.csv
pywisc/tools/tmpdata/wisc-4-es-ar-6_8-6_11.csv
pywisc/tools/tmpdata/wisc-4-es-ar-7_0-7_3.csv
pywisc/tools/tmpdata/wisc-4-es-ar-7_4-7_7.csv
pywisc/tools/tmpdata/wisc-4-es-ar-7_8-7_11.csv
pywisc/tools/tmpdata/wisc-4-es-ar-8_0-8_3.csv
pywisc/tools/tmpdata/wisc-4-es-ar-8_4-8_7.csv
pywisc/tools/tmpdata/wisc-4-es-ar-8_8-8_11.csv
pywisc/tools/tmpdata/wisc-4-es-ar-9_0-9_3.csv
pywisc/tools/tmpdata/wisc-4-es-ar-9_4-9_7.csv
pywisc/tools/tmpdata/wisc-4-es-ar-9_8-9_11.csv
pywisc-0.75.dist-info/METADATA
pywisc-0.75.dist-info/WHEEL
pywisc-0.75.dist-info/entry_points.txt
pywisc-0.75.dist-info/top_level.txt
pywisc-0.75.dist-info/RECORD
